sqlwrap/postgresql.py
sqlwrap-0.0.1.dist-info/LICENSE
sqlwrap-0.0.1.dist-info/WHEEL
sqlwrap-0.0.1.dist-info/METADATA
sqlwrap-0.0.1.dist-info/RECORD
